[
	{
		"Aeroport": "Tunis - Carthage",
		"Code": "TUN-sky",
		"Pays": "Tunisie"
	},
	{
		"Aeroport": "Alger - H. Boumédiène",
		"Code": "ALG-sky",
		"Pays": "Algérie"
	},
	{
		"Aeroport": "Annaba - Rabah-Bitat",
		"Code": "AAE-sky",
		"Pays": "Algérie"
	},
	{
		"Aeroport": "Constantine - M. Boudiaf",
		"Code": "CZL-sky",
		"Pays": "Algérie"
	},
	{
		"Aeroport": "Oran - A. Ben Bella",
		"Code": "ORN-sky",
		"Pays": "Algérie"
	},
	{
		"Aeroport": "Cologne/Bonn - K. Adenauer",
		"Code": "CGN-sky",
		"Pays": "Allemagne"
	},
	{
		"Aeroport": "Düsseldorf",
		"Code": "DUS-sky",
		"Pays": "Allemagne"
	},
	{
		"Aeroport": "Francfort",
		"Code": "FRA-sky",
		"Pays": "Allemagne"
	},
	{
		"Aeroport": "Munich - F. J. Strauß",
		"Code": "MUC-sky",
		"Pays": "Allemagne"
	},
	{
		"Aeroport": "Djeddah - Roi Abdelaziz",
		"Code": "JED-sky",
		"Pays": "Arabie saoudite"
	},
	{
		"Aeroport": "Médine - Prince M. Bin Abdulaziz",
		"Code": "MED-sky",
		"Pays": "Arabie saoudite"
	},
	{
		"Aeroport": "Vienne-Schwechat",
		"Code": "VIE-sky",
		"Pays": "Autriche"
	},
	{
		"Aeroport": "Bruxelles -  Charleroi",
		"Code": "CRL-sky",
		"Pays": "Belgique"
	},
	{
		"Aeroport": "Bruxelles - International",
		"Code": "BRU-sky",
		"Pays": "Belgique"
	},
	{
		"Aeroport": "Cotonou",
		"Code": "COO-sky",
		"Pays": "Bénin"
	},
	{
		"Aeroport": "Ouagadougou",
		"Code": "OUA-sky",
		"Pays": "Burkina Faso"
	},
	{
		"Aeroport": "Montréal - P.E.Trudeau",
		"Code": "YUL-sky",
		"Pays": "Canada"
	},
	{
		"Aeroport": "Abidjan - F. H. Boigny",
		"Code": "ABJ-sky",
		"Pays": "Côte d’Ivoire"
	},
	{
		"Aeroport": "Copenhague - Kastrup",
		"Code": "CPH-sky",
		"Pays": "Danemark"
	},
	{
		"Aeroport": "Le Caire",
		"Code": "CAI-sky",
		"Pays": "Égypte"
	},
	{
		"Aeroport": "Dubaï",
		"Code": "DXB-sky",
		"Pays": "Émirats arabes unis"
	},
	{
		"Aeroport": "Barcelone - El Prat",
		"Code": "BCN-sky",
		"Pays": "Espagne"
	},
	{
		"Aeroport": "Madrid - Barajas",
		"Code": "MAD-sky",
		"Pays": "Espagne"
	},
	{
		"Aeroport": "Bordeaux - Mérignac",
		"Code": "BOD-sky",
		"Pays": "France"
	},
	{
		"Aeroport": "Lyon - Saint Exupéry",
		"Code": "LYS-sky",
		"Pays": "France"
	},
	{
		"Aeroport": "Marseille - Provence",
		"Code": "MRS-sky",
		"Pays": "France"
	},
	{
		"Aeroport": "Nantes - Atlantique",
		"Code": "NTE-sky",
		"Pays": "France"
	},
	{
		"Aeroport": "Nice - Côte d'Azur",
		"Code": "NCE-sky",
		"Pays": "France"
	},
	{
		"Aeroport": "Paris - Charles de Gaulle",
		"Code": "CDG-sky",
		"Pays": "France"
	},
	{
		"Aeroport": "Paris - Orly",
		"Code": "ORY-sky",
		"Pays": "France"
	},
	{
		"Aeroport": "Strasbourg",
		"Code": "SXB-sky",
		"Pays": "France"
	},
	{
		"Aeroport": "Toulouse - Blagnac",
		"Code": "TLS-sky",
		"Pays": "France"
	},
	{
		"Aeroport": "Conakry",
		"Code": "CKY-sky",
		"Pays": "Guinée"
	},
	{
		"Aeroport": "Téhéran - Imam Khomeini",
		"Code": "IKA-sky",
		"Pays": "Iran"
	},
	{
		"Aeroport": "Bologne - Borgo Panigale",
		"Code": "BLQ-sky",
		"Pays": "Italie"
	},
	{
		"Aeroport": "Milan - Malpensa",
		"Code": "MXP-sky",
		"Pays": "Italie"
	},
	{
		"Aeroport": "Naples-Capodichino",
		"Code": "NAP-sky",
		"Pays": "Italie"
	},
	{
		"Aeroport": "Palerme Falcone - Borsellino",
		"Code": "PMO-sky",
		"Pays": "Italie"
	},
	{
		"Aeroport": "Rome - Léonard de Vinci/Fiumicino",
		"Code": "FCO-sky",
		"Pays": "Italie"
	},
	{
		"Aeroport": "Venise - Marco Polo",
		"Code": "VCE-sky",
		"Pays": "Italie"
	},
	{
		"Aeroport": "Amman - Reine Alia",
		"Code": "AMM-sky",
		"Pays": "Jordanie"
	},
	{
		"Aeroport": "Beyrouth - Rafic Hariri",
		"Code": "BEY-sky",
		"Pays": "Liban"
	},
	{
		"Aeroport": "El Beïda - Al Abraq",
		"Code": "LAQ-sky",
		"Pays": "Libye"
	},
	{
		"Aeroport": "Tobrouk",
		"Code": "TIP-sky",
		"Pays": "Libye"
	},
	{
		"Aeroport": "Tripoli - Mitiga",
		"Code": "MJI-sky",
		"Pays": "Libye"
	},
	{
		"Aeroport": "Bamako - M. Keïta",
		"Code": "BKO-sky",
		"Pays": "Mali"
	},
	{
		"Aeroport": "Malte",
		"Code": "MLA-sky",
		"Pays": "Malte"
	},
	{
		"Aeroport": "Casablanca - Mohammed V",
		"Code": "CMN-sky",
		"Pays": "Maroc"
	},
	{
		"Aeroport": "Nouakchott - Oumtounsy",
		"Code": "NKC-sky",
		"Pays": "Mauritanie"
	},
	{
		"Aeroport": "Niamey - D. Hamani",
		"Code": "NIM-sky",
		"Pays": "Niger"
	},
	{
		"Aeroport": "Amsterdam - Schiphol",
		"Code": "AMS-sky",
		"Pays": "Pays-Bas"
	},
	{
		"Aeroport": "Lisbonne - H. Delgado",
		"Code": "LIS-sky",
		"Pays": "Portugal"
	},
	{
		"Aeroport": "Doha - Hamad",
		"Code": "DOH-sky",
		"Pays": "Qatar"
	},
	{
		"Aeroport": "Londres - Gatwick",
		"Code": "LGW-sky",
		"Pays": "Royaume-Uni"
	},
	{
		"Aeroport": "Londres - Heathrow",
		"Code": "LHR-sky",
		"Pays": "Royaume-Uni"
	},
	{
		"Aeroport": "Moscou - Chérémétiévo",
		"Code": "SVO-sky",
		"Pays": "Russie"
	},
	{
		"Aeroport": "Dakar - B. Diagne",
		"Code": "DKRA-sky",
		"Pays": "Sénégal"
	},
	{
		"Aeroport": "Belgrade - Nikola Tesla",
		"Code": "BEG-sky",
		"Pays": "Serbie"
	},
	{
		"Aeroport": "Khartoum",
		"Code": "KRT-sky",
		"Pays": "Soudan"
	},
	{
		"Aeroport": "Stockholm - Arlanda",
		"Code": "ARN-sky",
		"Pays": "Suède"
	},
	{
		"Aeroport": "Genève-Cointrin",
		"Code": "GVA-sky",
		"Pays": "Suisse"
	},
	{
		"Aeroport": "Zurich",
		"Code": "ZRH-sky",
		"Pays": "Suisse"
	},
	{
		"Aeroport": "Djerba - Zarzis",
		"Code": "DJE-sky",
		"Pays": "Tunisie"
	},
	{
		"Aeroport": "Monastir - Hbib Bourguiba",
		"Code": "MIR-sky",
		"Pays": "Tunisie"
	},
	{
		"Aeroport": "Sfax - Thyna",
		"Code": "SFA-sky",
		"Pays": "Tunisie"
	},
	{
		"Aeroport": "Tozeur",
		"Code": "TOE-sky",
		"Pays": "Tunisie"
	},
	{
		"Aeroport": "Istanbul",
		"Code": "IST-sky",
		"Pays": "Turquie"
	}
]